ipwndfu/SHAtter.py
ipwndfu/__init__.py
ipwndfu/alloc8.py
ipwndfu/bin/24Kpwn-shellcode.bin
ipwndfu/bin/S5L8920-firmware
ipwndfu/bin/SHAtter-shellcode.bin
ipwndfu/bin/alloc8-shellcode.bin
ipwndfu/bin/checkm8_arm64.bin
ipwndfu/bin/checkm8_armv7.bin
ipwndfu/bin/checkm8_nopaddingcorruption_arm64.bin
ipwndfu/bin/ibss-flash-nor-shellcode.bin
ipwndfu/bin/limera1n-shellcode.bin
ipwndfu/bin/patch_ttbr_page_arm64.bin
ipwndfu/bin/steaks4uce-shellcode.bin
ipwndfu/bin/t8010_t8011_disable_wxn_arm64.bin
ipwndfu/bin/t8015_shellcode_arm64.bin
ipwndfu/bin/usb_0xA1_2_arm64.bin
ipwndfu/bin/usb_0xA1_2_armv7.bin
ipwndfu/checkm8.py
ipwndfu/device_platform.py
ipwndfu/dfu.py
ipwndfu/dfuexec.py
ipwndfu/ibootpatcher.py
ipwndfu/image3.py
ipwndfu/image3_24Kpwn.py
ipwndfu/ipwnrecovery.py
ipwndfu/limera1n.py
ipwndfu/main.py
ipwndfu/nop_image4.py
ipwndfu/nor.py
ipwndfu/recovery.py
ipwndfu/steaks4uce.py
ipwndfu/t8012_heap_fix.py
ipwndfu/usbexec.py
ipwndfu/utilities.py
libusbfinder/__init__.py
libusbfinder/bottles/libusb-1.0.19.mountain_lion.bottle.1.tar.gz
libusbfinder/bottles/libusb-1.0.20.mavericks.bottle.1.tar.gz
libusbfinder/bottles/libusb-1.0.21.yosemite.bottle.tar.gz
libusbfinder/bottles/libusb-1.0.22.el_capitan.bottle.tar.gz
libusbfinder/bottles/libusb-1.0.22.high_sierra.bottle.tar.gz
libusbfinder/bottles/libusb-1.0.22.mojave.bottle.tar.gz
libusbfinder/bottles/libusb-1.0.22.sierra.bottle.tar.gz
ipwndfu-2.0.0b5.dist-info/entry_points.txt
ipwndfu-2.0.0b5.dist-info/LICENSE
ipwndfu-2.0.0b5.dist-info/WHEEL
ipwndfu-2.0.0b5.dist-info/METADATA
ipwndfu-2.0.0b5.dist-info/RECORD
