Metadata-Version: 2.1
Name: ipwndfu
Version: 2.0.0b5
Summary: The DFU exploitation toolkit for Apple devices
Author: axi0mX
Author-email: axi0mXor@gmail.com
Requires-Python: >=3.8,<4.0
Classifier: Programming Language :: Python :: 3
Classifier: Programming Language :: Python :: 3.10
Classifier: Programming Language :: Python :: 3.8
Classifier: Programming Language :: Python :: 3.9
Requires-Dist: cryptography (>=36.0.1,<37.0.0)
Requires-Dist: pyusb (>=1.2.1,<2.0.0)
